plone.volto-5.2.2-py3.12-nspkg.pth
plone/volto/__init__.py
plone/volto/bbb.py
plone/volto/blocksuuidfixer.py
plone/volto/configure.zcml
plone/volto/content.py
plone/volto/controlpanel.py
plone/volto/dependencies.zcml
plone/volto/distributions.zcml
plone/volto/interfaces.py
plone/volto/linkintegrity.py
plone/volto/patches.py
plone/volto/patches.zcml
plone/volto/profiles.zcml
plone/volto/setuphandlers.py
plone/volto/summary.py
plone/volto/testing.py
plone/volto/transforms.py
plone/volto/upgrades.py
plone/volto/upgrades.zcml
plone/volto/behaviors/__init__.py
plone/volto/behaviors/configure.zcml
plone/volto/behaviors/kicker.py
plone/volto/behaviors/navtitle.py
plone/volto/behaviors/preview.py
plone/volto/behaviors/preview_link.py
plone/volto/browser/__init__.py
plone/volto/browser/breadcrumbs.py
plone/volto/browser/configure.zcml
plone/volto/browser/migrate_richtext.pt
plone/volto/browser/migrate_richtext.py
plone/volto/browser/migrate_to_volto.pt
plone/volto/browser/migrate_to_volto.py
plone/volto/browser/navigation.py
plone/volto/browser/voltobackendwarning.pt
plone/volto/browser/static/volto.svg
plone/volto/coresandbox/__init__.py
plone/volto/coresandbox/configure.zcml
plone/volto/coresandbox/example.py
plone/volto/coresandbox/vocabularies.py
plone/volto/cors/__init__.py
plone/volto/cors/configure.zcml
plone/volto/distributions/volto/image.png
plone/volto/distributions/volto/profiles.json
plone/volto/distributions/volto/schema.json
plone/volto/distributions/volto/content/discussions.json
plone/volto/distributions/volto/content/principals.json
plone/volto/distributions/volto/content/redirects.json
plone/volto/distributions/volto/content/relations.json
plone/volto/distributions/volto/content/translations.json
plone/volto/distributions/volto/content/content/__metadata__.json
plone/volto/distributions/volto/content/content/plone_site_root/data.json
plone/volto/indexers/__init__.py
plone/volto/indexers/configure.zcml
plone/volto/indexers/indexers.py
plone_volto-5.2.2.dist-info/METADATA
plone_volto-5.2.2.dist-info/WHEEL
plone_volto-5.2.2.dist-info/entry_points.txt
plone_volto-5.2.2.dist-info/namespace_packages.txt
plone_volto-5.2.2.dist-info/top_level.txt
plone_volto-5.2.2.dist-info/RECORD
