Metadata-Version: 2.4
Name: plone.volto
Version: 5.2.2
Summary: Volto integration add-on for Plone
Home-page: https://github.com/plone/plone.volto
Author: Plone Foundation
Author-email: tisto@plone.org
License: GPL version 2
Keywords: Python Plone CMS
Classifier: Development Status :: 5 - Production/Stable
Classifier: Environment :: Web Environment
Classifier: Framework :: Plone
Classifier: Framework :: Plone :: 6.1
Classifier: Programming Language :: Python
Classifier: Programming Language :: Python :: 3.10
Classifier: Programming Language :: Python :: 3.11
Classifier: Programming Language :: Python :: 3.12
Classifier: Operating System :: OS Independent
Classifier: License :: OSI Approved :: GNU General Public License v2 (GPLv2)
Requires-Python: >=3.10
Requires-Dist: collective.monkeypatcher
Requires-Dist: plone.api
Requires-Dist: plone.app.caching
Requires-Dist: plone.app.dexterity
Requires-Dist: plone.distribution
Requires-Dist: plone.restapi>=8.41.0
Requires-Dist: Products.CMFPlone
Requires-Dist: setuptools
Provides-Extra: test
Requires-Dist: responses; extra == "test"
Requires-Dist: plone.app.discussion; extra == "test"
Requires-Dist: plone.app.iterate; extra == "test"
Requires-Dist: plone.app.multilingual; extra == "test"
Requires-Dist: plone.app.robotframework; extra == "test"
Requires-Dist: plone.app.testing; extra == "test"
Requires-Dist: plone.app.upgrade; extra == "test"
Requires-Dist: plone.restapi[test]; extra == "test"
Requires-Dist: plone.testing; extra == "test"
Requires-Dist: Products.CMFPlacefulWorkflow; extra == "test"
Requires-Dist: pytest-plone>=0.5.0; extra == "test"
Dynamic: author
Dynamic: author-email
Dynamic: classifier
Dynamic: description
Dynamic: description-content-type
Dynamic: home-page
Dynamic: keywords
Dynamic: license
Dynamic: provides-extra
Dynamic: requires-dist
Dynamic: requires-python
Dynamic: summary
